day2/__init__.py
day2/_version.py
day2/exceptions.py
day2/session.py
day2/auth/__init__.py
day2/auth/credentials.py
day2/client/__init__.py
day2/client/base.py
day2/client/config.py
day2/models/__init__.py
day2/models/assessment.py
day2/models/tenant.py
day2/resources/__init__.py
day2/resources/assessment.py
day2/resources/tenant.py
day2_cli/__init__.py
day2_cli/cli.py
day2_cli/commands/__init__.py
day2_cli/commands/assessment.py
day2_cli/commands/auth.py
day2_cli/commands/tenant.py
day2_cli/utils/__init__.py
day2_cli/utils/config.py
day2_cli/utils/formatters.py
mc_day2-0.0.1.dev0.dist-info/licenses/LICENSE
mc_day2-0.0.1.dev0.dist-info/METADATA
mc_day2-0.0.1.dev0.dist-info/WHEEL
mc_day2-0.0.1.dev0.dist-info/entry_points.txt
mc_day2-0.0.1.dev0.dist-info/top_level.txt
mc_day2-0.0.1.dev0.dist-info/RECORD
