Metadata-Version: 2.4
Name: mc-day2
Version: 0.0.1.dev0
Summary: MontyCloud DAY2 SDK for Python
Author-email: MontyCloud <info@montycloud.com>
Requires-Python: >=3.11
License-File: LICENSE
Requires-Dist: requests>=2.31.0
Requires-Dist: pydantic>=2.5.0
Requires-Dist: typing-extensions>=4.8.0
Requires-Dist: tenacity>=8.2.3
Requires-Dist: jsonschema>=4.19.0
Requires-Dist: click>=8.1.7
Requires-Dist: rich>=13.5.2
Requires-Dist: typer>=0.9.0
Provides-Extra: dev
Requires-Dist: pytest>=7.4.0; extra == "dev"
Requires-Dist: pytest-cov>=4.1.0; extra == "dev"
Requires-Dist: black>=23.7.0; extra == "dev"
Requires-Dist: isort>=5.12.0; extra == "dev"
Requires-Dist: pylint>=2.17.5; extra == "dev"
Requires-Dist: mypy>=1.5.1; extra == "dev"
Requires-Dist: pre-commit>=3.3.3; extra == "dev"
Requires-Dist: twine>=4.0.2; extra == "dev"
Requires-Dist: build>=1.0.3; extra == "dev"
Requires-Dist: types-requests>=2.31.0; extra == "dev"
Requires-Dist: mkdocs>=1.5.0; extra == "dev"
Requires-Dist: mkdocs-material>=9.4.0; extra == "dev"
Requires-Dist: mkdocs-autorefs>=0.5.0; extra == "dev"
Requires-Dist: mkdocstrings>=0.22.0; extra == "dev"
Requires-Dist: mkdocstrings-python>=1.7.0; extra == "dev"
Provides-Extra: cli
Requires-Dist: click>=8.1.7; extra == "cli"
Requires-Dist: rich>=13.5.2; extra == "cli"
Requires-Dist: typer>=0.9.0; extra == "cli"
Dynamic: license-file
